apex/__init__.py
apex/__main__.py
apex/buffers.py
apex/cli.py
apex/nonrepeating_buffer.py
apex/plugin_loader.py
apex/util.py
apex/aprs/__init__.py
apex/aprs/aprs.py
apex/aprs/aprs_kiss.py
apex/aprs/constants.py
apex/aprs/decimal_degrees.py
apex/aprs/igate.py
apex/aprs/util.py
apex/kiss/__init__.py
apex/kiss/constants.py
apex/kiss/kiss.py
apex/kiss/kiss_serial.py
apex/kiss/kiss_tcp.py
apex/plugins/__init__.py
apex/plugins/apexparadigm/__init__.py
apex/plugins/beacon/__init__.py
apex/plugins/id/__init__.py
apex/plugins/status/__init__.py
apex/routing/__init__.py
apex/routing/route.py
apex_radio-0.0.5.dist-info/DESCRIPTION.rst
apex_radio-0.0.5.dist-info/METADATA
apex_radio-0.0.5.dist-info/RECORD
apex_radio-0.0.5.dist-info/WHEEL
apex_radio-0.0.5.dist-info/entry_points.txt
apex_radio-0.0.5.dist-info/metadata.json
apex_radio-0.0.5.dist-info/top_level.txt
