Metadata-Version: 2.0
Name: apex-radio
Version: 0.0.5
Summary: APEX reference implementation.
Home-page: http://ApexProtocol.com
Author: Jeffrey Phillips Freeman (WI2ARD)
Author-email: jeffrey.freeman@syncleus.com
License: Apache Software License
Download-URL: https://github.com/Syncleus/apex/archive/v0.0.5.tar.gz
Keywords: Ham Radio,APEX,APRS
Platform: UNKNOWN
Classifier: Development Status :: 2 - Pre-Alpha
Classifier: Intended Audience :: End Users/Desktop
Classifier: License :: OSI Approved :: Apache Software License
Classifier: Operating System :: Unix
Classifier: Operating System :: POSIX
Classifier: Operating System :: Microsoft :: Windows
Classifier: Programming Language :: Python
Classifier: Programming Language :: Python :: 2.7
Classifier: Programming Language :: Python :: 3
Classifier: Programming Language :: Python :: 3.3
Classifier: Programming Language :: Python :: 3.4
Classifier: Programming Language :: Python :: 3.5
Classifier: Programming Language :: Python :: Implementation :: PyPy
Classifier: Environment :: Console
Classifier: Environment :: No Input/Output (Daemon)
Classifier: Natural Language :: English
Classifier: Topic :: Communications :: Ham Radio
Requires-Dist: cachetools (>=1.1.5)
Requires-Dist: click (>=6.6)
Requires-Dist: pynmea2 (>=1.4.2)
Requires-Dist: pyserial (>=2.7)
Requires-Dist: requests (>=2.7.0)
Requires-Dist: six (>=1.10.0)
